atadata_cli/__init__.py
atadata_cli/cli.py
atadata_cli-1.0.1.dist-info/licenses/LICENSE
atadata_cli-1.0.1.dist-info/METADATA
atadata_cli-1.0.1.dist-info/WHEEL
atadata_cli-1.0.1.dist-info/entry_points.txt
atadata_cli-1.0.1.dist-info/top_level.txt
atadata_cli-1.0.1.dist-info/RECORD
