Metadata-Version: 2.4
Name: atadata-cli
Version: 1.0.1
Summary: Command line interface for AtaData Job Scheduler Backend API
Home-page: https://github.com/atadata/atadata-cli
Author: AtaData Team
Author-email: AtaData Team <support@atadata.com>
Maintainer-email: AtaData Team <support@atadata.com>
License: MIT
Project-URL: Homepage, https://github.com/atadata/atadata-cli
Project-URL: Documentation, https://github.com/atadata/atadata-cli#readme
Project-URL: Repository, https://github.com/atadata/atadata-cli
Project-URL: Bug Tracker, https://github.com/atadata/atadata-cli/issues
Keywords: cli,atadata,job-scheduler,api,backend,automation
Classifier: Development Status :: 5 - Production/Stable
Classifier: Intended Audience :: Developers
Classifier: Intended Audience :: System Administrators
Classifier: License :: OSI Approved :: MIT License
Classifier: Operating System :: OS Independent
Classifier: Programming Language :: Python :: 3
Classifier: Programming Language :: Python :: 3.8
Classifier: Programming Language :: Python :: 3.9
Classifier: Programming Language :: Python :: 3.10
Classifier: Programming Language :: Python :: 3.11
Classifier: Programming Language :: Python :: 3.12
Classifier: Topic :: Software Development :: Libraries :: Python Modules
Classifier: Topic :: System :: Systems Administration
Classifier: Topic :: Utilities
Requires-Python: >=3.8
License-File: LICENSE
Requires-Dist: requests>=2.25.0
Requires-Dist: urllib3>=1.26.0
Requires-Dist: python-dotenv>=0.19.0
Provides-Extra: dev
Requires-Dist: pytest>=6.0; extra == "dev"
Requires-Dist: pytest-cov>=2.0; extra == "dev"
Requires-Dist: black>=21.0; extra == "dev"
Requires-Dist: flake8>=3.8; extra == "dev"
Requires-Dist: mypy>=0.800; extra == "dev"
Provides-Extra: test
Requires-Dist: pytest>=6.0; extra == "test"
Requires-Dist: pytest-cov>=2.0; extra == "test"
Requires-Dist: pytest-mock>=3.0; extra == "test"
Provides-Extra: enhanced
Requires-Dist: colorama>=0.4.4; extra == "enhanced"
Requires-Dist: tabulate>=0.8.9; extra == "enhanced"
Requires-Dist: rich>=10.0.0; extra == "enhanced"
Dynamic: author
Dynamic: home-page
Dynamic: license-file
Dynamic: requires-python
